README.md
setup.py
j2db/__init__.py
j2db/auth.py
j2db/client.py
j2db/constants.py
j2db/db.py
j2db/errors.py
j2db/handler.py
j2db/models.py
j2db/router.py
j2db/server.py
j2db/toolbox.py
j2db.egg-info/PKG-INFO
j2db.egg-info/SOURCES.txt
j2db.egg-info/dependency_links.txt
j2db.egg-info/requires.txt
j2db.egg-info/top_level.txt