Metadata-Version: 1.1
Name: j2db
Version: 0.3.1
Summary: standard and safe way to upload your json to db
Home-page: https://github.com/williamfzc/j2db
Author: williamfzc
Author-email: fengzc@vip.qq.com
License: MIT
Platform: UNKNOWN
Classifier: License :: OSI Approved :: MIT License
Classifier: Programming Language :: Python
Classifier: Programming Language :: Python :: 3
